[1,["12c9dee9e@6c48a"],["_textureSource"],["cc.SpriteFrame","cc.SpriteAtlas"],0,[[[{"name":"LoadingMask7","rect":{"x":3,"y":3,"width":121,"height":126},"offset":{"x":0,"y":0},"originalSize":{"width":121,"height":126},"rotated":true,"capInsets":[0,0,0,0],"packable":true,"pixelsToUnit":100,"pivot":{"x":0.5,"y":0.5},"meshType":0}],[0],0,[0],[0],[0]],[[{"name":"auto-atlas","spriteFrames":["LoadingMask7","01fwHr9WFLQLUYtKVWn2xQ@f9941","LoadingMask10","180bE6oHFP76T4739GEQBp@f9941","LoadingMask11","2cHh5H1G9GnqNnVnObKumV@f9941","LoadingMask6","36ZY3i6nRL4oo19ZJ9kN6h@f9941","LoadingMask18","40pLoRK11MSqPskvPB5AMK@f9941","LoadingMask9","65RTwmneBAn6+i3x6AHgjM@f9941","LoadingMask14","6aKvMx7y9B/68uaxv9FB7U@f9941","LoadingMask16","6bSvOC3YNM9rMdakyQStka@f9941","LoadingMask1","7dJi7yjvtDs4M9FJeA8YDl@f9941","LoadingMask8","7e9mUpizxAj6XXACa+kQis@f9941","LoadingMask4","86pfX+x4tJt6ITU/Y1+z3r@f9941","LoadingMask3","8cngtWR0RBwbceJrx4elS+@f9941","LoadingMask12","9d7+MOBq9KIZQOq/KK5bxA@f9941","LoadingMask15","b1EqA/qqxNAJ1LTDIDIDCp@f9941","LoadingMask5","c7EPH8xw5NEp+K2+t9gRGq@f9941","LoadingMask19","c9Eu3EwwBAgILqg6gLHgtC@f9941","LoadingMask0","cd4QN8aRVGmYNY/RJOfP7W@f9941","LoadingMask17","e7y9uQZA1Bb54UOEVpHJ2O@f9941","LoadingMask13","fba0F3fH9D0q6fcGcgbhuM@f9941","LoadingMask2","fcz55l6Z9Pe5PXA4aXqrWc@f9941"]}],[1],0,[],[],[]],[[{"name":"LoadingMask10","rect":{"x":135,"y":3,"width":121,"height":126},"offset":{"x":0,"y":0},"originalSize":{"width":121,"height":126},"rotated":true,"capInsets":[0,0,0,0],"packable":true,"pixelsToUnit":100,"pivot":{"x":0.5,"y":0.5},"meshType":0}],[0],0,[0],[0],[0]],[[{"name":"LoadingMask11","rect":{"x":267,"y":3,"width":121,"height":126},"offset":{"x":0,"y":0},"originalSize":{"width":121,"height":126},"rotated":false,"capInsets":[0,0,0,0],"packable":true,"pixelsToUnit":100,"pivot":{"x":0.5,"y":0.5},"meshType":0}],[0],0,[0],[0],[0]],[[{"name":"LoadingMask6","rect":{"x":3,"y":130,"width":121,"height":126},"offset":{"x":0,"y":0},"originalSize":{"width":121,"height":126},"rotated":true,"capInsets":[0,0,0,0],"packable":true,"pixelsToUnit":100,"pivot":{"x":0.5,"y":0.5},"meshType":0}],[0],0,[0],[0],[0]],[[{"name":"LoadingMask18","rect":{"x":135,"y":130,"width":121,"height":126},"offset":{"x":0,"y":0},"originalSize":{"width":121,"height":126},"rotated":true,"capInsets":[0,0,0,0],"packable":true,"pixelsToUnit":100,"pivot":{"x":0.5,"y":0.5},"meshType":0}],[0],0,[0],[0],[0]],[[{"name":"LoadingMask9","rect":{"x":267,"y":135,"width":121,"height":126},"offset":{"x":0,"y":0},"originalSize":{"width":121,"height":126},"rotated":false,"capInsets":[0,0,0,0],"packable":true,"pixelsToUnit":100,"pivot":{"x":0.5,"y":0.5},"meshType":0}],[0],0,[0],[0],[0]],[[{"name":"LoadingMask14","rect":{"x":3,"y":257,"width":121,"height":126},"offset":{"x":0,"y":0},"originalSize":{"width":121,"height":126},"rotated":true,"capInsets":[0,0,0,0],"packable":true,"pixelsToUnit":100,"pivot":{"x":0.5,"y":0.5},"meshType":0}],[0],0,[0],[0],[0]],[[{"name":"LoadingMask16","rect":{"x":135,"y":257,"width":121,"height":126},"offset":{"x":0,"y":0},"originalSize":{"width":121,"height":126},"rotated":true,"capInsets":[0,0,0,0],"packable":true,"pixelsToUnit":100,"pivot":{"x":0.5,"y":0.5},"meshType":0}],[0],0,[0],[0],[0]],[[{"name":"LoadingMask1","rect":{"x":267,"y":267,"width":121,"height":126},"offset":{"x":0,"y":0},"originalSize":{"width":121,"height":126},"rotated":false,"capInsets":[0,0,0,0],"packable":true,"pixelsToUnit":100,"pivot":{"x":0.5,"y":0.5},"meshType":0}],[0],0,[0],[0],[0]],[[{"name":"LoadingMask8","rect":{"x":3,"y":384,"width":121,"height":126},"offset":{"x":0,"y":0},"originalSize":{"width":121,"height":126},"rotated":true,"capInsets":[0,0,0,0],"packable":true,"pixelsToUnit":100,"pivot":{"x":0.5,"y":0.5},"meshType":0}],[0],0,[0],[0],[0]],[[{"name":"LoadingMask4","rect":{"x":135,"y":384,"width":121,"height":126},"offset":{"x":0,"y":0},"originalSize":{"width":121,"height":126},"rotated":true,"capInsets":[0,0,0,0],"packable":true,"pixelsToUnit":100,"pivot":{"x":0.5,"y":0.5},"meshType":0}],[0],0,[0],[0],[0]],[[{"name":"LoadingMask3","rect":{"x":267,"y":399,"width":121,"height":126},"offset":{"x":0,"y":0},"originalSize":{"width":121,"height":126},"rotated":false,"capInsets":[0,0,0,0],"packable":true,"pixelsToUnit":100,"pivot":{"x":0.5,"y":0.5},"meshType":0}],[0],0,[0],[0],[0]],[[{"name":"LoadingMask12","rect":{"x":3,"y":511,"width":121,"height":126},"offset":{"x":0,"y":0},"originalSize":{"width":121,"height":126},"rotated":true,"capInsets":[0,0,0,0],"packable":true,"pixelsToUnit":100,"pivot":{"x":0.5,"y":0.5},"meshType":0}],[0],0,[0],[0],[0]],[[{"name":"LoadingMask15","rect":{"x":135,"y":511,"width":121,"height":126},"offset":{"x":0,"y":0},"originalSize":{"width":121,"height":126},"rotated":true,"capInsets":[0,0,0,0],"packable":true,"pixelsToUnit":100,"pivot":{"x":0.5,"y":0.5},"meshType":0}],[0],0,[0],[0],[0]],[[{"name":"LoadingMask5","rect":{"x":267,"y":531,"width":121,"height":126},"offset":{"x":0,"y":0},"originalSize":{"width":121,"height":126},"rotated":false,"capInsets":[0,0,0,0],"packable":true,"pixelsToUnit":100,"pivot":{"x":0.5,"y":0.5},"meshType":0}],[0],0,[0],[0],[0]],[[{"name":"LoadingMask19","rect":{"x":3,"y":638,"width":121,"height":126},"offset":{"x":0,"y":0},"originalSize":{"width":121,"height":126},"rotated":true,"capInsets":[0,0,0,0],"packable":true,"pixelsToUnit":100,"pivot":{"x":0.5,"y":0.5},"meshType":0}],[0],0,[0],[0],[0]],[[{"name":"LoadingMask0","rect":{"x":135,"y":638,"width":121,"height":126},"offset":{"x":0,"y":0},"originalSize":{"width":121,"height":126},"rotated":true,"capInsets":[0,0,0,0],"packable":true,"pixelsToUnit":100,"pivot":{"x":0.5,"y":0.5},"meshType":0}],[0],0,[0],[0],[0]],[[{"name":"LoadingMask17","rect":{"x":267,"y":663,"width":121,"height":126},"offset":{"x":0,"y":0},"originalSize":{"width":121,"height":126},"rotated":false,"capInsets":[0,0,0,0],"packable":true,"pixelsToUnit":100,"pivot":{"x":0.5,"y":0.5},"meshType":0}],[0],0,[0],[0],[0]],[[{"name":"LoadingMask13","rect":{"x":3,"y":765,"width":121,"height":126},"offset":{"x":0,"y":0},"originalSize":{"width":121,"height":126},"rotated":true,"capInsets":[0,0,0,0],"packable":true,"pixelsToUnit":100,"pivot":{"x":0.5,"y":0.5},"meshType":0}],[0],0,[0],[0],[0]],[[{"name":"LoadingMask2","rect":{"x":135,"y":765,"width":121,"height":126},"offset":{"x":0,"y":0},"originalSize":{"width":121,"height":126},"rotated":true,"capInsets":[0,0,0,0],"packable":true,"pixelsToUnit":100,"pivot":{"x":0.5,"y":0.5},"meshType":0}],[0],0,[0],[0],[0]]]]
